rgb565_converter/__init__.py
rgb565_converter/converter.py
rgb565_converter-1.4.0.dist-info/LICENSE
rgb565_converter-1.4.0.dist-info/METADATA
rgb565_converter-1.4.0.dist-info/WHEEL
rgb565_converter-1.4.0.dist-info/entry_points.txt
rgb565_converter-1.4.0.dist-info/top_level.txt
rgb565_converter-1.4.0.dist-info/RECORD
