Metadata-Version: 2.1
Name: rgb565-converter
Version: 1.4.0
Summary: Convert a file from png to rgb565 (cpp) and vice versa.
Home-page: https://github.com/CommanderRedYT/rgb565-converter
Author: CommanderRedYT
License: GPLv3
Requires-Python: >=3.7
License-File: LICENSE
Requires-Dist: argparse ~=1.4.0
Requires-Dist: Pillow ==10.0.1
